{
  "title": "Backups",
  "category": "tools",
  "source": "tools/BackUps.md",
  "slides": [
    {
      "id": "bcdd8c25-d32d-45cd-94fa-8ce00b0ff522",
      "layout": "center",
      "bgType": "gradient",
      "bgColor": "#080b08",
      "bgGradient": "linear-gradient(160deg,#020602 0%,#051505 40%,#020a02 100%)",
      "bgImage": "",
      "titleText": "Backups",
      "titleColor": "#00ff41",
      "titleSize": 52,
      "subtitleText": "",
      "subtitleColor": "#2a6b3a",
      "bodyText": "A resilient operator maintains at least two backup layers. Working with exploits, unstable tools, and live payloads makes system breakage inevitable — a proper backup strategy enables fast rollback and recovery.",
      "bodyColor": "#7ab87a",
      "bodySize": 22,
      "bullets": [],
      "codeText": "",
      "codeLang": "",
      "imageUrl": "",
      "showTitle": true,
      "showSubtitle": false,
      "showBody": true,
      "showBullets": false,
      "showCode": false,
      "showImage": false,
      "textAlign": "center",
      "fontFamily": "'Courier New', 'Fira Mono', monospace",
      "transition": "zoom"
    },
    {
      "id": "db862905-556b-43c6-8c4c-fd88c4c5b08c",
      "layout": "top",
      "bgType": "gradient",
      "bgColor": "#080b08",
      "bgGradient": "linear-gradient(160deg,#030803 0%,#061206 100%)",
      "bgImage": "",
      "titleText": "Approaches",
      "titleColor": "#00ff41",
      "titleSize": 48,
      "subtitleText": "",
      "subtitleColor": "#2a6b3a",
      "bodyText": "",
      "bodyColor": "#7ab87a",
      "bodySize": 22,
      "bullets": [
        "Method  ::  Tools  ::  Best For",
        "Snapshots  ::  Snapper, Timeshift, ZFS  ::  Instant OS rollbacks",
        "Encrypted backups  ::  BorgBackup, Restic, Duplicity  ::  Long-term secure storage",
        "GUI helpers  ::  Pika-Backup, KBackup, Déjà Dup  ::  Beginner-friendly workflows",
        "Cloud / sync  ::  Syncthing, Nextcloud, Rclone  ::  Multi-device resilience",
        "Disk imaging  ::  Clonezilla, Rescuezilla, dd  ::  Full forensic clones"
      ],
      "codeText": "",
      "codeLang": "",
      "imageUrl": "",
      "showTitle": true,
      "showSubtitle": false,
      "showBody": false,
      "showBullets": true,
      "showCode": false,
      "showImage": false,
      "textAlign": "left",
      "fontFamily": "'Courier New', 'Fira Mono', monospace",
      "transition": "slide-r"
    },
    {
      "id": "c6299426-feb0-4925-9c4e-33835a34e563",
      "layout": "top",
      "bgType": "gradient",
      "bgColor": "#080b08",
      "bgGradient": "linear-gradient(160deg,#030803 0%,#061206 100%)",
      "bgImage": "",
      "titleText": "Snapshot-Based",
      "titleColor": "#00ff41",
      "titleSize": 48,
      "subtitleText": "",
      "subtitleColor": "#2a6b3a",
      "bodyText": "Freeze OS state; roll back instantly when an experiment breaks the system.",
      "bodyColor": "#7ab87a",
      "bodySize": 22,
      "bullets": [],
      "codeText": "",
      "codeLang": "",
      "imageUrl": "",
      "showTitle": true,
      "showSubtitle": false,
      "showBody": true,
      "showBullets": false,
      "showCode": false,
      "showImage": false,
      "textAlign": "left",
      "fontFamily": "'Courier New', 'Fira Mono', monospace",
      "transition": "slide-r"
    },
    {
      "id": "f68043b8-698b-4572-a0a2-ee7079e69dc0",
      "layout": "top",
      "bgType": "gradient",
      "bgColor": "#080b08",
      "bgGradient": "linear-gradient(160deg,#030803 0%,#061206 100%)",
      "bgImage": "",
      "titleText": "Snapper",
      "titleColor": "#00ff41",
      "titleSize": 36,
      "subtitleText": "",
      "subtitleColor": "#2a6b3a",
      "bodyText": "",
      "bodyColor": "#7ab87a",
      "bodySize": 22,
      "bullets": [
        "Snapshot manager for btrfs/LVM.",
        "Integrates with GRUB — bootable into older snapshots.",
        "Automatic pre/post hooks for pacman -Syu.",
        "Requires btrfs or LVM."
      ],
      "codeText": "",
      "codeLang": "",
      "imageUrl": "",
      "showTitle": true,
      "showSubtitle": false,
      "showBody": false,
      "showBullets": true,
      "showCode": false,
      "showImage": false,
      "textAlign": "left",
      "fontFamily": "'Courier New', 'Fira Mono', monospace",
      "transition": "slide-r"
    },
    {
      "id": "7f58b296-63e6-4ea8-b043-cf9127500406",
      "layout": "top",
      "bgType": "gradient",
      "bgColor": "#080b08",
      "bgGradient": "linear-gradient(160deg,#030803 0%,#061206 100%)",
      "bgImage": "",
      "titleText": "Timeshift",
      "titleColor": "#00ff41",
      "titleSize": 36,
      "subtitleText": "",
      "subtitleColor": "#2a6b3a",
      "bodyText": "",
      "bodyColor": "#7ab87a",
      "bodySize": 22,
      "bullets": [
        "System snapshot tool (rsync or btrfs mode).",
        "Simple UI with scheduled snapshots.",
        "Focuses on system files only, not home directory.",
        "Beginner-friendly; good for post-update rollbacks."
      ],
      "codeText": "",
      "codeLang": "",
      "imageUrl": "",
      "showTitle": true,
      "showSubtitle": false,
      "showBody": false,
      "showBullets": true,
      "showCode": false,
      "showImage": false,
      "textAlign": "left",
      "fontFamily": "'Courier New', 'Fira Mono', monospace",
      "transition": "slide-r"
    },
    {
      "id": "1531d62a-8c5b-4d53-b14f-91e31b8ca000",
      "layout": "top",
      "bgType": "gradient",
      "bgColor": "#080b08",
      "bgGradient": "linear-gradient(160deg,#030803 0%,#061206 100%)",
      "bgImage": "",
      "titleText": "ZFS Auto-Snapshot",
      "titleColor": "#00ff41",
      "titleSize": 36,
      "subtitleText": "",
      "subtitleColor": "#2a6b3a",
      "bodyText": "",
      "bodyColor": "#7ab87a",
      "bodySize": 22,
      "bullets": [
        "Automated snapshots for ZFS pools.",
        "Built-in compression and strong resilience.",
        "Higher RAM usage; licensing complications on Linux.",
        "Best suited for servers or large storage arrays."
      ],
      "codeText": "",
      "codeLang": "",
      "imageUrl": "",
      "showTitle": true,
      "showSubtitle": false,
      "showBody": false,
      "showBullets": true,
      "showCode": false,
      "showImage": false,
      "textAlign": "left",
      "fontFamily": "'Courier New', 'Fira Mono', monospace",
      "transition": "slide-r"
    },
    {
      "id": "ce79158f-93aa-4bcf-8948-bcc132673000",
      "layout": "top",
      "bgType": "gradient",
      "bgColor": "#080b08",
      "bgGradient": "linear-gradient(160deg,#030803 0%,#061206 100%)",
      "bgImage": "",
      "titleText": "Encrypted Backup Tools",
      "titleColor": "#00ff41",
      "titleSize": 48,
      "subtitleText": "",
      "subtitleColor": "#2a6b3a",
      "bodyText": "Long-term, portable, and secure backups.",
      "bodyColor": "#7ab87a",
      "bodySize": 22,
      "bullets": [],
      "codeText": "",
      "codeLang": "",
      "imageUrl": "",
      "showTitle": true,
      "showSubtitle": false,
      "showBody": true,
      "showBullets": false,
      "showCode": false,
      "showImage": false,
      "textAlign": "left",
      "fontFamily": "'Courier New', 'Fira Mono', monospace",
      "transition": "slide-r"
    },
    {
      "id": "ba8ffa27-edc4-421e-a7b7-4fd86f1ecb19",
      "layout": "top",
      "bgType": "gradient",
      "bgColor": "#080b08",
      "bgGradient": "linear-gradient(160deg,#030803 0%,#061206 100%)",
      "bgImage": "",
      "titleText": "BorgBackup",
      "titleColor": "#00ff41",
      "titleSize": 36,
      "subtitleText": "",
      "subtitleColor": "#2a6b3a",
      "bodyText": "",
      "bodyColor": "#7ab87a",
      "bodySize": 22,
      "bullets": [
        "Deduplicating, compressing, and encrypting backup tool.",
        "Strong encryption; highly space-efficient.",
        "Proven in production environments.",
        "CLI-heavy; recommended for ops laptops backing up to encrypted drives or a VPS."
      ],
      "codeText": "",
      "codeLang": "",
      "imageUrl": "",
      "showTitle": true,
      "showSubtitle": false,
      "showBody": false,
      "showBullets": true,
      "showCode": false,
      "showImage": false,
      "textAlign": "left",
      "fontFamily": "'Courier New', 'Fira Mono', monospace",
      "transition": "slide-r"
    },
    {
      "id": "a13ec383-8f55-4456-8d04-d8af751b4040",
      "layout": "top",
      "bgType": "gradient",
      "bgColor": "#080b08",
      "bgGradient": "linear-gradient(160deg,#030803 0%,#061206 100%)",
      "bgImage": "",
      "titleText": "Restic",
      "titleColor": "#00ff41",
      "titleSize": 36,
      "subtitleText": "",
      "subtitleColor": "#2a6b3a",
      "bodyText": "",
      "bodyColor": "#7ab87a",
      "bodySize": 22,
      "bullets": [
        "Modern backup tool; simpler configuration than Borg.",
        "Fast restores; supports cloud backends (S3, GDrive, and others).",
        "Deduplication is less aggressive than Borg.",
        "Good for personal cloud backups with minimal setup."
      ],
      "codeText": "",
      "codeLang": "",
      "imageUrl": "",
      "showTitle": true,
      "showSubtitle": false,
      "showBody": false,
      "showBullets": true,
      "showCode": false,
      "showImage": false,
      "textAlign": "left",
      "fontFamily": "'Courier New', 'Fira Mono', monospace",
      "transition": "slide-r"
    },
    {
      "id": "9fd44dc8-56fc-42ee-8652-47155704d982",
      "layout": "top",
      "bgType": "gradient",
      "bgColor": "#080b08",
      "bgGradient": "linear-gradient(160deg,#030803 0%,#061206 100%)",
      "bgImage": "",
      "titleText": "Duplicity",
      "titleColor": "#00ff41",
      "titleSize": 36,
      "subtitleText": "",
      "subtitleColor": "#2a6b3a",
      "bodyText": "",
      "bodyColor": "#7ab87a",
      "bodySize": 22,
      "bullets": [
        "Incremental encrypted backups using rsync and GPG.",
        "Strong encryption via GPG keys.",
        "Slower than Borg or Restic.",
        "Suitable if GPG is already a core part of your workflow."
      ],
      "codeText": "",
      "codeLang": "",
      "imageUrl": "",
      "showTitle": true,
      "showSubtitle": false,
      "showBody": false,
      "showBullets": true,
      "showCode": false,
      "showImage": false,
      "textAlign": "left",
      "fontFamily": "'Courier New', 'Fira Mono', monospace",
      "transition": "slide-r"
    },
    {
      "id": "8546eb6f-1ccf-40d5-8882-bc9058e9ffc9",
      "layout": "top",
      "bgType": "gradient",
      "bgColor": "#080b08",
      "bgGradient": "linear-gradient(160deg,#030803 0%,#061206 100%)",
      "bgImage": "",
      "titleText": "GUI-Based",
      "titleColor": "#00ff41",
      "titleSize": 48,
      "subtitleText": "",
      "subtitleColor": "#2a6b3a",
      "bodyText": "Accessible interfaces for common backup workflows.",
      "bodyColor": "#7ab87a",
      "bodySize": 22,
      "bullets": [],
      "codeText": "",
      "codeLang": "",
      "imageUrl": "",
      "showTitle": true,
      "showSubtitle": false,
      "showBody": true,
      "showBullets": false,
      "showCode": false,
      "showImage": false,
      "textAlign": "left",
      "fontFamily": "'Courier New', 'Fira Mono', monospace",
      "transition": "slide-r"
    },
    {
      "id": "ea8ffb1f-990a-4160-8ba6-6057be413cc3",
      "layout": "top",
      "bgType": "gradient",
      "bgColor": "#080b08",
      "bgGradient": "linear-gradient(160deg,#030803 0%,#061206 100%)",
      "bgImage": "",
      "titleText": "Pika-Backup",
      "titleColor": "#00ff41",
      "titleSize": 36,
      "subtitleText": "",
      "subtitleColor": "#2a6b3a",
      "bodyText": "",
      "bodyColor": "#7ab87a",
      "bodySize": 22,
      "bullets": [
        "GNOME application wrapping BorgBackup.",
        "Provides Borg’s power without the CLI.",
        "Best for daily home-folder and documents backups."
      ],
      "codeText": "",
      "codeLang": "",
      "imageUrl": "",
      "showTitle": true,
      "showSubtitle": false,
      "showBody": false,
      "showBullets": true,
      "showCode": false,
      "showImage": false,
      "textAlign": "left",
      "fontFamily": "'Courier New', 'Fira Mono', monospace",
      "transition": "slide-r"
    },
    {
      "id": "c2778742-5dae-437a-ad36-ec25a40f030b",
      "layout": "top",
      "bgType": "gradient",
      "bgColor": "#080b08",
      "bgGradient": "linear-gradient(160deg,#030803 0%,#061206 100%)",
      "bgImage": "",
      "titleText": "KBackup",
      "titleColor": "#00ff41",
      "titleSize": 36,
      "subtitleText": "",
      "subtitleColor": "#2a6b3a",
      "bodyText": "",
      "bodyColor": "#7ab87a",
      "bodySize": 22,
      "bullets": [
        "KDE-native backup tool.",
        "Simple folder backups; less capable than Borg or Restic.",
        "Suited for KDE users needing quick config backups."
      ],
      "codeText": "",
      "codeLang": "",
      "imageUrl": "",
      "showTitle": true,
      "showSubtitle": false,
      "showBody": false,
      "showBullets": true,
      "showCode": false,
      "showImage": false,
      "textAlign": "left",
      "fontFamily": "'Courier New', 'Fira Mono', monospace",
      "transition": "slide-r"
    },
    {
      "id": "a04ec42b-162d-4c4e-baad-54283db86324",
      "layout": "top",
      "bgType": "gradient",
      "bgColor": "#080b08",
      "bgGradient": "linear-gradient(160deg,#030803 0%,#061206 100%)",
      "bgImage": "",
      "titleText": "Déjà Dup",
      "titleColor": "#00ff41",
      "titleSize": 36,
      "subtitleText": "",
      "subtitleColor": "#2a6b3a",
      "bodyText": "",
      "bodyColor": "#7ab87a",
      "bodySize": 22,
      "bullets": [
        "GNOME frontend for Duplicity.",
        "Very beginner-friendly; one-click cloud backup.",
        "Limited configuration; slower than alternatives."
      ],
      "codeText": "",
      "codeLang": "",
      "imageUrl": "",
      "showTitle": true,
      "showSubtitle": false,
      "showBody": false,
      "showBullets": true,
      "showCode": false,
      "showImage": false,
      "textAlign": "left",
      "fontFamily": "'Courier New', 'Fira Mono', monospace",
      "transition": "slide-r"
    },
    {
      "id": "d620763e-6d0c-4232-8d8c-0818535c5f72",
      "layout": "top",
      "bgType": "gradient",
      "bgColor": "#080b08",
      "bgGradient": "linear-gradient(160deg,#030803 0%,#061206 100%)",
      "bgImage": "",
      "titleText": "Cloud / Sync",
      "titleColor": "#00ff41",
      "titleSize": 48,
      "subtitleText": "",
      "subtitleColor": "#2a6b3a",
      "bodyText": "Keep files mirrored across devices.",
      "bodyColor": "#7ab87a",
      "bodySize": 22,
      "bullets": [],
      "codeText": "",
      "codeLang": "",
      "imageUrl": "",
      "showTitle": true,
      "showSubtitle": false,
      "showBody": true,
      "showBullets": false,
      "showCode": false,
      "showImage": false,
      "textAlign": "left",
      "fontFamily": "'Courier New', 'Fira Mono', monospace",
      "transition": "slide-r"
    },
    {
      "id": "c19c9aba-be78-412b-91f5-846d8086610a",
      "layout": "top",
      "bgType": "gradient",
      "bgColor": "#080b08",
      "bgGradient": "linear-gradient(160deg,#030803 0%,#061206 100%)",
      "bgImage": "",
      "titleText": "Syncthing",
      "titleColor": "#00ff41",
      "titleSize": 36,
      "subtitleText": "",
      "subtitleColor": "#2a6b3a",
      "bodyText": "",
      "bodyColor": "#7ab87a",
      "bodySize": 22,
      "bullets": [
        "Peer-to-peer file synchronisation; no central server.",
        "End-to-end encrypted.",
        "Not a true backup — accidental deletions propagate to all peers.",
        "Best for syncing notes and scripts between a laptop and VPS."
      ],
      "codeText": "",
      "codeLang": "",
      "imageUrl": "",
      "showTitle": true,
      "showSubtitle": false,
      "showBody": false,
      "showBullets": true,
      "showCode": false,
      "showImage": false,
      "textAlign": "left",
      "fontFamily": "'Courier New', 'Fira Mono', monospace",
      "transition": "slide-r"
    },
    {
      "id": "d9d65d16-ead1-42e9-a617-a50b962088c5",
      "layout": "top",
      "bgType": "gradient",
      "bgColor": "#080b08",
      "bgGradient": "linear-gradient(160deg,#030803 0%,#061206 100%)",
      "bgImage": "",
      "titleText": "Nextcloud",
      "titleColor": "#00ff41",
      "titleSize": 36,
      "subtitleText": "",
      "subtitleColor": "#2a6b3a",
      "bodyText": "",
      "bodyColor": "#7ab87a",
      "bodySize": 22,
      "bullets": [
        "Self-hosted cloud storage (Dropbox alternative).",
        "Full ecosystem: calendar, contacts, web and mobile clients.",
        "Requires a server; heavier setup.",
        "Suited for private cloud storage and team collaboration."
      ],
      "codeText": "",
      "codeLang": "",
      "imageUrl": "",
      "showTitle": true,
      "showSubtitle": false,
      "showBody": false,
      "showBullets": true,
      "showCode": false,
      "showImage": false,
      "textAlign": "left",
      "fontFamily": "'Courier New', 'Fira Mono', monospace",
      "transition": "slide-r"
    },
    {
      "id": "a33c65fa-0295-437c-98f3-c82b6b5d1de2",
      "layout": "top",
      "bgType": "gradient",
      "bgColor": "#080b08",
      "bgGradient": "linear-gradient(160deg,#030803 0%,#061206 100%)",
      "bgImage": "",
      "titleText": "Rclone",
      "titleColor": "#00ff41",
      "titleSize": 36,
      "subtitleText": "",
      "subtitleColor": "#2a6b3a",
      "bodyText": "",
      "bodyColor": "#7ab87a",
      "bodySize": 22,
      "bullets": [
        "CLI tool for syncing to cloud providers.",
        "Supports nearly every backend (S3, GDrive, Mega, and others).",
        "Advanced users syncing encrypted repositories to cloud storage."
      ],
      "codeText": "",
      "codeLang": "",
      "imageUrl": "",
      "showTitle": true,
      "showSubtitle": false,
      "showBody": false,
      "showBullets": true,
      "showCode": false,
      "showImage": false,
      "textAlign": "left",
      "fontFamily": "'Courier New', 'Fira Mono', monospace",
      "transition": "slide-r"
    },
    {
      "id": "33ce4553-5aec-495c-9647-e6ccff0c0c67",
      "layout": "top",
      "bgType": "gradient",
      "bgColor": "#080b08",
      "bgGradient": "linear-gradient(160deg,#030803 0%,#061206 100%)",
      "bgImage": "",
      "titleText": "Forensic / Full-Disk Imaging",
      "titleColor": "#00ff41",
      "titleSize": 48,
      "subtitleText": "",
      "subtitleColor": "#2a6b3a",
      "bodyText": "Last-resort recovery: clone an entire disk bit by bit.",
      "bodyColor": "#7ab87a",
      "bodySize": 22,
      "bullets": [],
      "codeText": "",
      "codeLang": "",
      "imageUrl": "",
      "showTitle": true,
      "showSubtitle": false,
      "showBody": true,
      "showBullets": false,
      "showCode": false,
      "showImage": false,
      "textAlign": "left",
      "fontFamily": "'Courier New', 'Fira Mono', monospace",
      "transition": "slide-r"
    },
    {
      "id": "54c63415-3b07-439b-bde3-745d52b46170",
      "layout": "top",
      "bgType": "gradient",
      "bgColor": "#080b08",
      "bgGradient": "linear-gradient(160deg,#030803 0%,#061206 100%)",
      "bgImage": "",
      "titleText": "Clonezilla",
      "titleColor": "#00ff41",
      "titleSize": 36,
      "subtitleText": "",
      "subtitleColor": "#2a6b3a",
      "bodyText": "",
      "bodyColor": "#7ab87a",
      "bodySize": 22,
      "bullets": [
        "Partition and disk imaging tool.",
        "Reliable and fast; not incremental.",
        "Used for creating a golden OS image before hacking labs."
      ],
      "codeText": "",
      "codeLang": "",
      "imageUrl": "",
      "showTitle": true,
      "showSubtitle": false,
      "showBody": false,
      "showBullets": true,
      "showCode": false,
      "showImage": false,
      "textAlign": "left",
      "fontFamily": "'Courier New', 'Fira Mono', monospace",
      "transition": "slide-r"
    },
    {
      "id": "00fc6b46-91f0-4acc-bcf6-682f7b0d6900",
      "layout": "top",
      "bgType": "gradient",
      "bgColor": "#080b08",
      "bgGradient": "linear-gradient(160deg,#030803 0%,#061206 100%)",
      "bgImage": "",
      "titleText": "Rescuezilla",
      "titleColor": "#00ff41",
      "titleSize": 36,
      "subtitleText": "",
      "subtitleColor": "#2a6b3a",
      "bodyText": "",
      "bodyColor": "#7ab87a",
      "bodySize": 22,
      "bullets": [
        "Clonezilla with a graphical interface.",
        "Easier and safer for infrequent use.",
        "Slightly slower than CLI Clonezilla."
      ],
      "codeText": "",
      "codeLang": "",
      "imageUrl": "",
      "showTitle": true,
      "showSubtitle": false,
      "showBody": false,
      "showBullets": true,
      "showCode": false,
      "showImage": false,
      "textAlign": "left",
      "fontFamily": "'Courier New', 'Fira Mono', monospace",
      "transition": "slide-r"
    },
    {
      "id": "89bb1a15-3ee8-40ce-9470-7722aba2d914",
      "layout": "top",
      "bgType": "gradient",
      "bgColor": "#080b08",
      "bgGradient": "linear-gradient(160deg,#030803 0%,#061206 100%)",
      "bgImage": "",
      "titleText": "dd",
      "titleColor": "#00ff41",
      "titleSize": 36,
      "subtitleText": "",
      "subtitleColor": "#2a6b3a",
      "bodyText": "",
      "bodyColor": "#7ab87a",
      "bodySize": 22,
      "bullets": [
        "Raw block-level copy tool built into Linux.",
        "Extreme power: one incorrect argument can wipe the entire target disk.",
        "Reserved for forensic imaging by experienced operators."
      ],
      "codeText": "",
      "codeLang": "",
      "imageUrl": "",
      "showTitle": true,
      "showSubtitle": false,
      "showBody": false,
      "showBullets": true,
      "showCode": false,
      "showImage": false,
      "textAlign": "left",
      "fontFamily": "'Courier New', 'Fira Mono', monospace",
      "transition": "slide-r"
    },
    {
      "id": "7eb6ef85-e46c-4cfd-86fe-402f8a1e0625",
      "layout": "top",
      "bgType": "gradient",
      "bgColor": "#080b08",
      "bgGradient": "linear-gradient(160deg,#030803 0%,#061206 100%)",
      "bgImage": "",
      "titleText": "Notes",
      "titleColor": "#00ff41",
      "titleSize": 48,
      "subtitleText": "",
      "subtitleColor": "#2a6b3a",
      "bodyText": "",
      "bodyColor": "#7ab87a",
      "bodySize": 22,
      "bullets": [
        "Combine at least two layers (e.g., snapshots + encrypted backup).",
        "Test restores regularly — an untested backup is not a backup.",
        "Store encrypted backup keys separately from the backup itself."
      ],
      "codeText": "",
      "codeLang": "",
      "imageUrl": "",
      "showTitle": true,
      "showSubtitle": false,
      "showBody": false,
      "showBullets": true,
      "showCode": false,
      "showImage": false,
      "textAlign": "left",
      "fontFamily": "'Courier New', 'Fira Mono', monospace",
      "transition": "slide-r"
    },
    {
      "id": "d3e431ad-7bbe-460c-9fb6-78600f22e675",
      "layout": "top",
      "bgType": "gradient",
      "bgColor": "#080b08",
      "bgGradient": "linear-gradient(160deg,#030803 0%,#061206 100%)",
      "bgImage": "",
      "titleText": "Related Guides",
      "titleColor": "#00ff41",
      "titleSize": 48,
      "subtitleText": "",
      "subtitleColor": "#2a6b3a",
      "bodyText": "",
      "bodyColor": "#7ab87a",
      "bodySize": 22,
      "bullets": [
        "Guide",
        "Encrypt your backups  ::  GPG",
        "Back to host setup  ::  Arch Quality of Life"
      ],
      "codeText": "",
      "codeLang": "",
      "imageUrl": "",
      "showTitle": true,
      "showSubtitle": false,
      "showBody": false,
      "showBullets": true,
      "showCode": false,
      "showImage": false,
      "textAlign": "left",
      "fontFamily": "'Courier New', 'Fira Mono', monospace",
      "transition": "slide-r"
    }
  ],
  "transition": "fade"
}